cardex/__init__.py
cardex/backend/__init__.py
cardex/backend/dbsync.py
cardex/dataclasses/__init__.py
cardex/dataclasses/datums.py
cardex/dataclasses/models.py
cardex/dexs/__init__.py
cardex/dexs/abstract_classes.py
cardex/dexs/base_classes.py
cardex/dexs/minswap.py
cardex/dexs/muesli.py
cardex/dexs/spectrum.py
cardex/dexs/sundae.py
cardex/dexs/vyfi.py
cardex/dexs/wingriders.py
cardex/utility.py
cardex-0.1.0.dist-info/LICENSE
cardex-0.1.0.dist-info/METADATA
cardex-0.1.0.dist-info/WHEEL
cardex-0.1.0.dist-info/RECORD
