Metadata-Version: 2.1
Name: cardex
Version: 0.1.0
Summary: 
Author: Elder Millenial
Author-email: eldermillenial@protonmail.com
Requires-Python: >=3.10,<4.0
Classifier: Programming Language :: Python :: 3
Classifier: Programming Language :: Python :: 3.10
Classifier: Programming Language :: Python :: 3.11
Classifier: Programming Language :: Python :: 3.12
Requires-Dist: psycopg[binary,pool] (>=3.1.13,<4.0.0)
Requires-Dist: pycardano (==0.10.0)
Requires-Dist: pydantic (>=2.5.2,<3.0.0)
Requires-Dist: python-dotenv (==0.21.1)
Requires-Dist: requests (>=2.31.0,<3.0.0)
